skget/__init__.py
skget/common.py
skget/main.py
skget/settings.py
skget/skills.py
skget-0.6.0.dist-info/licenses/LICENSE
skget-0.6.0.dist-info/METADATA
skget-0.6.0.dist-info/WHEEL
skget-0.6.0.dist-info/entry_points.txt
skget-0.6.0.dist-info/top_level.txt
skget-0.6.0.dist-info/RECORD
