Metadata-Version: 2.4
Name: skget
Version: 0.6.0
Summary: A CLI to add skills to your coding agents
Project-URL: Repository, https://github.com/czheo/skget
Requires-Python: >=3.10
License-File: LICENSE
Requires-Dist: click>=8.1.7
Requires-Dist: python-frontmatter>=1.1.0
Requires-Dist: tabulate>=0.9.0
Requires-Dist: textual>=7.3.0
Dynamic: license-file
